AUTHORS
CHANGELOG.txt
DESCRIPTION
LICENSE
MANIFEST.in
README.rst
setup.cfg
setup.py
aps_production/__init__.py
aps_production/admin.py
aps_production/models.py
aps_production/urls.py
aps_production/views.py
aps_production/migrations/0001_initial.py
aps_production/migrations/0002_auto__chg_field_orderrun_quantity_out__chg_field_orderrun_quantity_des.py
aps_production/migrations/__init__.py
aps_production/static/.empty
aps_production/static/aps_production/.empty
aps_production/templates/aps_production/.empty
aps_production/tests/.coverage
aps_production/tests/.coveragerc
aps_production/tests/__init__.py
aps_production/tests/factories.py
aps_production/tests/models_tests.py
aps_production/tests/runtests.py
aps_production/tests/south_settings.py
aps_production/tests/test_settings.py
aps_production/tests/urls.py
aps_production/tests/test_app/__init__.py
aps_production/tests/test_app/models.py
aps_production/tests/test_app/templates/400.html
aps_production/tests/test_app/templates/500.html
django_aps_production.egg-info/PKG-INFO
django_aps_production.egg-info/SOURCES.txt
django_aps_production.egg-info/dependency_links.txt
django_aps_production.egg-info/requires.txt
django_aps_production.egg-info/top_level.txt