Metadata-Version: 1.0
Name: django-aps-production
Version: 0.1
Summary: A Django app to log and plan production processes
